fractalai/__init__.py
fractalai/__version__.py
fractalai/classifier/__init__.py
fractalai/classifier/cls_decoder.py
fractalai/classifier/model.py
fractalai/classifier/remap.py
fractalai/csv_utils.py
fractalai/datasets/__init__.py
fractalai/datasets/agu.py
fractalai/datasets/dataloader.py
fractalai/datasets/dataset.py
fractalai/datasets/helper.py
fractalai/datasets/seversteal.py
fractalai/engine/__init__.py
fractalai/engine/infer.py
fractalai/engine/trainer.py
fractalai/engine/utils.py
fractalai/labelme2folder.py
fractalai/sanity.py
fractalai/segmenter/__init__.py
fractalai/segmenter/model.py
fractalai/utils/__init__.py
fractalai/utils/cls_losses.py
fractalai/utils/metrics.py
fractalai/utils/optims.py
fractalai/utils/timer.py
fractalai/visual.py
fractalai-0.1.0.dist-info/entry_points.txt
fractalai-0.1.0.dist-info/WHEEL
fractalai-0.1.0.dist-info/METADATA
fractalai-0.1.0.dist-info/RECORD
