Metadata-Version: 2.1
Name: fractalai
Version: 0.1.0
Summary: Integrated image classification and semantic segmentation package
License: Apache-2.0
Author: PrakashJay
Author-email: vanapalli.prakash@fractal.ai
Requires-Python: ==3.7.0
Classifier: License :: OSI Approved :: Apache Software License
Classifier: Programming Language :: Python :: 3
Classifier: Programming Language :: Python :: 3.7
Requires-Dist: EasyDict (>=1.9,<2.0)
Requires-Dist: albumentations (>=0.4.1,<0.5.0)
Requires-Dist: click (>=7.0,<8.0)
Requires-Dist: efficientnet_pytorch (>=0.6.3,<0.7.0)
Requires-Dist: hyperdash (>=0.15.3,<0.16.0)
Requires-Dist: loguru (>=0.3.2,<0.4.0)
Requires-Dist: opencv-python (>=4.1,<5.0)
Requires-Dist: pandas (>=0.25.2,<0.26.0)
Requires-Dist: pretrainedmodels (>=0.7.4,<0.8.0)
Requires-Dist: pycocotools (>=2.0,<3.0)
Requires-Dist: pytorch-lightning (>=0.7.1,<0.8.0)
Requires-Dist: scikit-learn (>=0.21.3,<0.22.0)
Requires-Dist: segmentation_models_pytorch (>=0.1.0,<0.2.0)
Requires-Dist: torch (==1.4.0)
Requires-Dist: torchvision (>=0.5.0,<0.6.0)
